{
    "track": {
        "mmo": 20,
        "trackTitle": "Before I Forget",
        "releaseYear": 2005,
        "duration": 268,
        "iconBass": "Bass",
        "iconDrum": "Drum",
        "iconGuitar": "Guitar",
        "iconVocals": "Vocals",
        "key": "Db",
        "majorMinor": "Minor",
        "intensities": {
            "bd": 2,
            "proBass": 5,
            "proDrums": 5,
            "vocals": 2,
            "proGuitar": 5,
            "guitar": 5,
            "drums": 5,
            "bass": 4
        },
        "BPM": 140,
        "artistName": "Slipknot",
        "ageRating": "E",
        "albumArtFilename": "9u5gcllaw7gppx4v-512x512-d571f0a36478.jpg",
        "recordingCode": "NLA320420824",
        "songUUID": "f61c437c-71fd-4c7d-a8bf-2285ecceff46",
        "trackIndex": "210"
    },
    "_activeDate": "2025-03-11T08:00:00.000Z",
    "lastModified": "2025-12-09T15:16:41.662Z"
}