{
    "track": {
        "mmo": 82,
        "trackTitle": "Broccoli",
        "releaseYear": 2016,
        "duration": 223,
        "iconBass": "Bass",
        "iconDrum": "Drum",
        "iconGuitar": "Keyboard",
        "iconVocals": "Vocals",
        "key": "Eb",
        "majorMinor": "Major",
        "intensities": {
            "bd": 2,
            "proBass": 1,
            "proDrums": 0,
            "vocals": 4,
            "proGuitar": 2,
            "guitar": 2,
            "drums": 1,
            "bass": 1
        },
        "BPM": 146,
        "artistName": "DRAM ft. Lil Yachty",
        "ageRating": "T",
        "albumArtFilename": "aywqms9qo3hfulvt-512x512-b6a389f2a8f5.jpg",
        "recordingCode": "USUYG1099931",
        "songUUID": "32d83723-3aeb-49e1-a817-a14421a3f6af",
        "trackIndex": "284"
    },
    "_activeDate": "2025-03-11T08:00:00.000Z",
    "lastModified": "2025-12-02T21:27:49.712Z"
}