{
    "track": {
        "mmo": 27,
        "trackTitle": "i",
        "releaseYear": 2015,
        "duration": 237,
        "iconBass": "Bass",
        "iconDrum": "Drum",
        "iconGuitar": "Guitar",
        "iconVocals": "Vocals",
        "key": "C",
        "majorMinor": "Minor",
        "intensities": {
            "bd": 3,
            "proBass": 5,
            "proDrums": 5,
            "vocals": 6,
            "proGuitar": 4,
            "guitar": 3,
            "drums": 5,
            "bass": 6
        },
        "BPM": 122,
        "artistName": "Kendrick Lamar",
        "ageRating": "E",
        "albumArtFilename": "e9grrtvjygnzygyd-512x512-556e08ad44a8.jpg",
        "recordingCode": "USUM71414121",
        "songUUID": "2a845ec5-463a-4a6a-b55d-7c9ee3c12cfe",
        "trackIndex": "110"
    },
    "_activeDate": "2025-03-11T08:00:00.000Z",
    "lastModified": "2025-10-24T16:57:39.701Z"
}