{
    "track": {
        "trackTitle": "PLAYERS",
        "releaseYear": 2025,
        "duration": 205,
        "iconBass": "Bass",
        "iconDrum": "Drum",
        "iconGuitar": "Keyboard",
        "iconVocals": "Vocals",
        "key": "E",
        "majorMinor": "Major",
        "intensities": {
            "bd": 5,
            "proBass": 5,
            "proDrums": 5,
            "vocals": 4,
            "proGuitar": 6,
            "guitar": 6,
            "drums": 5,
            "bass": 5
        },
        "BPM": 93,
        "artistName": "YOASOBI",
        "ageRating": "E",
        "albumArtFilename": "vwzshmcosdatklvy-512x512-e103a270525e.jpg",
        "recordingCode": "JPP302500188",
        "songUUID": "96a52bf8-eac2-45d9-8a5e-d0a6a05a3e6e",
        "trackIndex": "654"
    },
    "_activeDate": "2025-08-19T14:30:00.000Z",
    "lastModified": "2025-10-29T17:05:01.156Z"
}